easyback/__init__.py
easyback/context.py
easyback/engine.py
easyback/broker/__init__.py
easyback/broker/account.py
easyback/gateway/__init__.py
easyback/gateway/datasource.py
easyback/strategy/__init__.py
easyback/strategy/strategy.py
easyback/utils/__init__.py
easyback/utils/common_util.py
easyback/vex/__init__.py
easyback/vex/quote.py
easyback/vex/trade.py
easyback-0.1.1.dist-info/METADATA
easyback-0.1.1.dist-info/WHEEL
easyback-0.1.1.dist-info/top_level.txt
easyback-0.1.1.dist-info/RECORD
